{
  "skeleton": {
    "hash": "AO015KrOWWzrTPHT7GwIibn9UX4",
    "spine": "2.1.27",
    "width": 330.73681640625,
    "height": 371.7589111328125
  },
  "bones": [
    {
      "name": "root"
    },
    {
      "name": "fxchest",
      "parent": "root",
      "x": -14.296417236328125,
      "y": 179.68174743652344
    },
    {
      "name": "fxhead",
      "parent": "root",
      "x": 4,
      "y": 258
    },
    {
      "name": "fxskill",
      "parent": "root"
    },
    {
      "name": "hips",
      "parent": "root",
      "x": -8.907401084899902,
      "y": 129.9246063232422
    },
    {
      "name": "left_foot",
      "parent": "root",
      "length": 16.044700622558594,
      "x": 56.28358459472656,
      "y": 17.833629608154297,
      "rotation": -52.408905029296875
    },
    {
      "name": "right_foot",
      "parent": "root",
      "length": 18.679397583007812,
      "x": -28.136409759521484,
      "y": 16.426616668701172,
      "rotation": -151.60540771484375
    },
    {
      "name": "belt",
      "parent": "hips",
      "x": -6.565997123718262,
      "y": 7.035003662109375
    },
    {
      "name": "left_lower_leg",
      "parent": "left_foot",
      "length": 56.010284423828125,
      "x": -54.937461853027344,
      "y": 10.91970443725586,
      "rotation": -11.56997299194336
    },
    {
      "name": "right_lower_leg",
      "parent": "right_foot",
      "length": 58.01210021972656,
      "x": -14.412708282470703,
      "y": -56.19321060180664,
      "rotation": 75.43421936035156
    },
    {
      "name": "spine",
      "parent": "hips",
      "length": 61.32054138183594,
      "x": -1.7677888870239258,
      "y": 12.944320678710938,
      "rotation": 88.18169403076172
    },
    {
      "name": "fxdot",
      "parent": "spine",
      "x": 18.965835571289062,
      "y": -26.088298797607422,
      "rotation": -88.18169403076172
    },
    {
      "name": "head",
      "parent": "spine",
      "length": 34.53741455078125,
      "x": 61.31907653808594,
      "y": -0.4254951477050781,
      "rotation": -10.344857215881348
    },
    {
      "name": "left_leg",
      "parent": "left_lower_leg",
      "length": 63.3427734375,
      "x": -63.35122299194336,
      "y": -0.3809051513671875
    },
    {
      "name": "left_shoulder",
      "parent": "spine",
      "length": 28.159608840942383,
      "x": 57.58050537109375,
      "y": -8.15805435180664,
      "rotation": -79.73485565185547
    },
    {
      "name": "right_leg",
      "parent": "right_lower_leg",
      "length": 58.51985168457031,
      "x": -44.84107971191406,
      "y": 37.60930252075195,
      "rotation": -39.84992218017578
    },
    {
      "name": "right_shoulder",
      "parent": "spine",
      "length": 22.004745483398438,
      "x": 56.178802490234375,
      "y": 6.545312881469727,
      "rotation": 83.21102142333984
    },
    {
      "name": "hat",
      "parent": "head",
      "length": 55.46042251586914,
      "x": 44.575592041015625,
      "y": -4.452342987060547,
      "rotation": 18.917312622070312
    },
    {
      "name": "left_arm",
      "parent": "left_shoulder",
      "length": 34.47682189941406,
      "x": 9.910709381103516,
      "y": -8.901092529296875,
      "rotation": -48.16548538208008
    },
    {
      "name": "left_hair",
      "parent": "head",
      "length": 13.192781448364258,
      "x": 36.288848876953125,
      "y": -26.693645477294922,
      "rotation": -157.7333984375
    },
    {
      "name": "right_arm",
      "parent": "right_shoulder",
      "length": 48.6957893371582,
      "x": 20.037200927734375,
      "y": 9.893600463867188,
      "rotation": 56.518653869628906
    },
    {
      "name": "right_hair01",
      "parent": "head",
      "length": 24.625518798828125,
      "x": 33.5863037109375,
      "y": 14.972049713134766,
      "rotation": 180
    },
    {
      "name": "scarf",
      "parent": "head",
      "length": 9.198433876037598,
      "x": 7.333770751953125,
      "y": -1.5529861450195312,
      "rotation": 160.91322326660156
    },
    {
      "name": "left_forearm",
      "parent": "left_arm",
      "length": 27.18173599243164,
      "x": 40.391048431396484,
      "y": 0.6630706787109375,
      "rotation": 127.49079895019531
    },
    {
      "name": "right_forearm",
      "parent": "right_arm",
      "length": 25.29623031616211,
      "x": 48.69554138183594,
      "y": -0.1572723388671875,
      "rotation": -135.228271484375
    },
    {
      "name": "left_hand",
      "parent": "left_forearm",
      "length": 14.871611595153809,
      "x": 27.177143096923828,
      "y": -0.07562255859375,
      "rotation": 34.58451843261719
    },
    {
      "name": "right_hand",
      "parent": "right_forearm",
      "length": 13.121305465698242,
      "x": 25.52996826171875,
      "y": -0.029079437255859375,
      "rotation": -5.3977484703063965
    },
    {
      "name": "dagger",
      "parent": "right_hand",
      "length": 94.47679901123047,
      "x": -4.686431884765625,
      "y": -4.9068450927734375,
      "rotation": -2.254574775695801
    }
  ],
  "slots": [
    {
      "name": "shadow",
      "bone": "root",
      "attachment": "shadow"
    },
    {
      "name": "combat",
      "bone": "root"
    },
    {
      "name": "right_boot",
      "bone": "right_lower_leg",
      "attachment": "kneeright"
    },
    {
      "name": "legright",
      "bone": "right_leg",
      "attachment": "legright"
    },
    {
      "name": "left_boot",
      "bone": "left_lower_leg",
      "attachment": "kneeleft"
    },
    {
      "name": "legleft",
      "bone": "left_leg",
      "attachment": "legleft"
    },
    {
      "name": "pants",
      "bone": "hips",
      "attachment": "skirt"
    },
    {
      "name": "scarf",
      "bone": "scarf"
    },
    {
      "name": "left_arm",
      "bone": "left_arm",
      "attachment": "shoulderleft"
    },
    {
      "name": "shoulderright",
      "bone": "right_shoulder",
      "attachment": "torso"
    },
    {
      "name": "shirt",
      "bone": "spine",
      "attachment": "shirt"
    },
    {
      "name": "belt",
      "bone": "belt",
      "attachment": "buckle"
    },
    {
      "name": "right_arm",
      "bone": "right_arm",
      "attachment": "shoulderright"
    },
    {
      "name": "left_hair",
      "bone": "left_hair",
      "attachment": "hairback"
    },
    {
      "name": "face",
      "bone": "head",
      "attachment": "face"
    },
    {
      "name": "right_hair",
      "bone": "right_hair01",
      "attachment": "bang"
    },
    {
      "name": "hat",
      "bone": "hat",
      "attachment": "hat"
    },
    {
      "name": "left_forearm",
      "bone": "left_forearm",
      "attachment": "armleft"
    },
    {
      "name": "left_hand",
      "bone": "left_hand",
      "attachment": "handleft"
    },
    {
      "name": "right_forearm",
      "bone": "right_forearm",
      "attachment": "armright"
    },
    {
      "name": "footright",
      "bone": "right_foot",
      "attachment": "footright"
    },
    {
      "name": "dagger",
      "bone": "dagger",
      "attachment": "staff"
    },
    {
      "name": "right_hand",
      "bone": "right_hand",
      "attachment": "handright"
    },
    {
      "name": "footleft",
      "bone": "left_foot",
      "attachment": "footleft"
    }
  ],
  "skins": {
    "default": {
      "shadow": {
        "shadow": {
          "x": 11.847972869873047,
          "scaleX": 0.550000011920929,
          "scaleY": 0.5,
          "width": 355,
          "height": 63
        }
      },
      "right_boot": {
        "kneeright": {
          "x": 19.521560668945312,
          "y": 1.839421272277832,
          "scaleX": 0.4193563461303711,
          "scaleY": 0.4193563461303711,
          "rotation": 73.64632415771484,
          "width": 49,
          "height": 143
        }
      },
      "legright": {
        "legright": {
          "x": 25.775606155395508,
          "y": 1.4586257934570312,
          "scaleX": 0.4433427155017853,
          "scaleY": 0.5093264579772949,
          "rotation": 103.51390075683594,
          "width": 59,
          "height": 128
        }
      },
      "left_boot": {
        "kneeleft": {
          "x": 5.420161247253418,
          "y": -6.336978435516357,
          "scaleX": 0.3970892131328583,
          "scaleY": 0.4699939787387848,
          "rotation": 83.75713348388672,
          "width": 54,
          "height": 100
        }
      },
      "legleft": {
        "legleft": {
          "x": 31.720855712890625,
          "y": -2.970231056213379,
          "scaleX": 0.44719207286834717,
          "scaleY": 0.44719207286834717,
          "rotation": 70.4190673828125,
          "width": 88,
          "height": 135
        }
      },
      "pants": {
        "skirt": {
          "x": 1.5347309112548828,
          "y": -6.800423622131348,
          "scaleX": 0.43900203704833984,
          "scaleY": 0.43900203704833984,
          "width": 157,
          "height": 71
        }
      },
      "left_arm": {
        "shoulderleft": {
          "x": 17.065467834472656,
          "y": -2.0268588066101074,
          "scaleX": 0.44927847385406494,
          "scaleY": 0.44927847385406494,
          "rotation": 39.340789794921875,
          "width": 125,
          "height": 100
        }
      },
      "shoulderright": {
        "torso": {
          "x": -6.809852600097656,
          "y": 5.6999053955078125,
          "scaleX": 0.4082082211971283,
          "scaleY": 0.4082082211971283,
          "rotation": -171.39271545410156,
          "width": 117,
          "height": 109
        }
      },
      "shirt": {
        "shirt": {
          "x": 18.893760681152344,
          "y": -1.7557272911071777,
          "scaleX": 0.4386301338672638,
          "scaleY": 0.4386301338672638,
          "rotation": -88.18169403076172,
          "width": 114,
          "height": 113
        }
      },
      "belt": {
        "buckle": {
          "x": 8.185369491577148,
          "y": 3.3106837272644043,
          "scaleX": 0.44518399238586426,
          "scaleY": 0.44518399238586426,
          "width": 117,
          "height": 54
        }
      },
      "right_arm": {
        "shoulderright": {
          "x": 7.617332458496094,
          "y": 11.468368530273438,
          "scaleX": 0.4125014841556549,
          "scaleY": 0.4125014841556549,
          "rotation": 138.18353271484375,
          "width": 83,
          "height": 103
        }
      },
      "left_hair": {
        "hairback": {
          "x": 20.906497955322266,
          "y": -31.527891159057617,
          "scaleX": 0.5272703170776367,
          "scaleY": 0.5272703170776367,
          "rotation": 79.89656066894531,
          "width": 95,
          "height": 110
        }
      },
      "face": {
        "face": {
          "x": 20.617027282714844,
          "y": 0.8433284163475037,
          "scaleX": 0.5015251636505127,
          "scaleY": 0.5015251636505127,
          "rotation": -77.83683776855469,
          "width": 116,
          "height": 95
        }
      },
      "right_hair": {
        "bang": {
          "x": 11.182998657226562,
          "y": 20.84762954711914,
          "scaleX": 0.459553986787796,
          "scaleY": 0.459553986787796,
          "rotation": 102.16314697265625,
          "width": 156,
          "height": 113
        }
      },
      "hat": {
        "hat": {
          "x": 14.826594352722168,
          "y": 2.1806297302246094,
          "scaleX": 0.4682305157184601,
          "scaleY": 0.4682305157184601,
          "rotation": -102.33502197265625,
          "width": 303,
          "height": 169
        }
      },
      "left_forearm": {
        "armleft": {
          "x": 18.07439422607422,
          "y": 5.001406669616699,
          "scaleX": 0.480233371257782,
          "scaleY": 0.480233371257782,
          "rotation": -96.6919174194336,
          "width": 63,
          "height": 100
        }
      },
      "left_hand": {
        "handleft": {
          "x": 16.595108032226562,
          "y": -0.7931098937988281,
          "scaleX": 0.4778780937194824,
          "scaleY": 0.4778780937194824,
          "rotation": -122.35667419433594,
          "width": 65,
          "height": 59
        }
      },
      "right_forearm": {
        "armright": {
          "x": 0.531224250793457,
          "y": -19.04596710205078,
          "scaleX": 0.48700088262557983,
          "scaleY": 0.48700088262557983,
          "rotation": -92.68310546875,
          "width": 68,
          "height": 94
        }
      },
      "footright": {
        "footright": {
          "x": 6.314311504364014,
          "y": -12.922926902770996,
          "scaleX": 0.43245285749435425,
          "scaleY": 0.43245285749435425,
          "rotation": 146.96365356445312,
          "width": 62,
          "height": 96
        }
      },
      "dagger": {
        "staff": {
          "x": 6.688640594482422,
          "y": -16.58216094970703,
          "scaleX": 0.4984228014945984,
          "scaleY": 0.4984228014945984,
          "rotation": -118.26397705078125,
          "width": 433,
          "height": 550
        }
      },
      "right_hand": {
        "handright": {
          "x": -10.759774208068848,
          "y": -23.81106948852539,
          "scaleX": 0.477414071559906,
          "scaleY": 0.477414071559906,
          "rotation": -105.31275939941406,
          "width": 58,
          "height": 54
        }
      },
      "footleft": {
        "footleft": {
          "x": -23.379234313964844,
          "y": -10.492410659790039,
          "scaleX": 0.46772730350494385,
          "scaleY": 0.46772730350494385,
          "rotation": 52.408905029296875,
          "width": 79,
          "height": 90
        }
      }
    }
  },
  "animations": {
    "combat": {
      "slots": {
        "belt": {
          "color": [
            {
              "time": 0,
              "color": "ffffffff"
            }
          ]
        },
        "dagger": {
          "color": [
            {
              "time": 0,
              "color": "ffffffff"
            }
          ]
        },
        "face": {
          "color": [
            {
              "time": 0,
              "color": "ffffffff"
            }
          ]
        },
        "hat": {
          "color": [
            {
              "time": 0,
              "color": "ffffffff"
            }
          ]
        },
        "left_arm": {
          "color": [
            {
              "time": 0,
              "color": "ffffffff"
            }
          ]
        },
        "left_boot": {
          "color": [
            {
              "time": 0,
              "color": "ffffffff"
            }
          ]
        },
        "left_forearm": {
          "color": [
            {
              "time": 0,
              "color": "ffffffff"
            }
          ]
        },
        "left_hair": {
          "color": [
            {
              "time": 0,
              "color": "ffffffff"
            }
          ]
        },
        "left_hand": {
          "color": [
            {
              "time": 0,
              "color": "ffffffff"
            }
          ]
        },
        "pants": {
          "color": [
            {
              "time": 0,
              "color": "ffffffff"
            }
          ]
        },
        "right_arm": {
          "color": [
            {
              "time": 0,
              "color": "ffffffff"
            }
          ]
        },
        "right_boot": {
          "color": [
            {
              "time": 0,
              "color": "ffffffff"
            }
          ]
        },
        "right_forearm": {
          "color": [
            {
              "time": 0,
              "color": "ffffffff"
            }
          ]
        },
        "right_hair": {
          "color": [
            {
              "time": 0,
              "color": "ffffffff"
            }
          ]
        },
        "right_hand": {
          "color": [
            {
              "time": 0,
              "color": "ffffffff"
            }
          ]
        },
        "scarf": {
          "color": [
            {
              "time": 0,
              "color": "ffffffff"
            }
          ]
        },
        "shirt": {
          "color": [
            {
              "time": 0,
              "color": "ffffffff"
            }
          ]
        }
      },
      "bones": {
        "belt": {
          "rotate": [
            {
              "time": 0,
              "angle": 0,
              "curve": "stepped"
            },
            {
              "time": 0.46666666865348816,
              "angle": 0,
              "curve": "stepped"
            },
            {
              "time": 0.9333333373069763,
              "angle": 0
            }
          ],
          "translate": [
            {
              "time": 0,
              "x": 0,
              "y": 0,
              "curve": [
                0.238571435213089,
                -0.9088858962059021,
                0.75,
                1
              ]
            },
            {
              "time": 0.46666666865348816,
              "x": -0.7135310173034668,
              "y": 0.99493408203125,
              "curve": [
                0.24142856895923615,
                -0.3963759243488312,
                0.7642857432365417,
                1
              ]
            },
            {
              "time": 0.9333333373069763,
              "x": 0,
              "y": 0
            }
          ],
          "scale": [
            {
              "time": 0,
              "x": 1,
              "y": 1,
              "curve": "stepped"
            },
            {
              "time": 0.46666666865348816,
              "x": 1,
              "y": 1,
              "curve": "stepped"
            },
            {
              "time": 0.9333333373069763,
              "x": 1,
              "y": 1
            }
          ]
        },
        "dagger": {
          "rotate": [
            {
              "time": 0,
              "angle": 0,
              "curve": "stepped"
            },
            {
              "time": 0.9333333373069763,
              "angle": 0
            }
          ],
          "translate": [
            {
              "time": 0,
              "x": 0,
              "y": 0,
              "curve": "stepped"
            },
            {
              "time": 0.9333333373069763,
              "x": 0,
              "y": 0
            }
          ],
          "scale": [
            {
              "time": 0,
              "x": 1,
              "y": 1,
              "curve": "stepped"
            },
            {
              "time": 0.9333333373069763,
              "x": 1,
              "y": 1
            }
          ]
        },
        "head": {
          "rotate": [
            {
              "time": 0,
              "angle": 0.07720375061035156,
              "curve": [
                0.36747005581855774,
                0.6315790414810181,
                0.70481938123703,
                1
              ]
            },
            {
              "time": 0.06666667014360428,
              "angle": 0
            },
            {
              "time": 0.5333333611488342,
              "angle": 1,
              "curve": [
                0.24378108978271484,
                0,
                0.6965174078941345,
                0.7777777910232544
              ]
            },
            {
              "time": 0.9333333373069763,
              "angle": 0.07720375061035156
            }
          ],
          "translate": [
            {
              "time": 0,
              "x": -0.017154693603515625,
              "y": 0.002458333969116211,
              "curve": [
                0.36747005581855774,
                0.6315790414810181,
                0.70481938123703,
                1
              ]
            },
            {
              "time": 0.06666667014360428,
              "x": 0,
              "y": 0,
              "curve": [
                0.3528571128845215,
                -0.5800899267196655,
                0.7099999785423279,
                1.0000003576278687
              ]
            },
            {
              "time": 0.5333333611488342,
              "x": -0.2222137451171875,
              "y": 0.03184223175048828,
              "curve": [
                0.24378108978271484,
                0,
                0.6965174078941345,
                0.7777777910232544
              ]
            },
            {
              "time": 0.9333333373069763,
              "x": -0.017154693603515625,
              "y": 0.002458333969116211
            }
          ],
          "scale": [
            {
              "time": 0,
              "x": 0.9978184700012207,
              "y": 0.9978184700012207,
              "curve": [
                0.34293946623802185,
                0.6243200302124023,
                0.676814615726471,
                1
              ]
            },
            {
              "time": 0.06666667014360428,
              "x": 1,
              "y": 1,
              "curve": [
                0.3528571128845215,
                -0.5800899267196655,
                0.7099999785423279,
                1.0000003576278687
              ]
            },
            {
              "time": 0.5333333611488342,
              "x": 0.9803922176361084,
              "y": 0.9803922176361084,
              "curve": [
                0.34692004323005676,
                -0.5439064502716064,
                0.6974517107009888,
                0.6482765078544617
              ]
            },
            {
              "time": 0.9333333373069763,
              "x": 0.9978184700012207,
              "y": 0.9978184700012207
            }
          ]
        },
        "hat": {
          "rotate": [
            {
              "time": 0,
              "angle": -0.0003523826599121094,
              "curve": [
                0.37643659114837646,
                0.6111112236976624,
                0.7183906435966492,
                1
              ]
            },
            {
              "time": 0.10000000149011612,
              "angle": 0,
              "curve": [
                0.22142857313156128,
                -0.8121442794799805,
                0.7528571486473083,
                1
              ]
            },
            {
              "time": 0.5666666626930237,
              "angle": -0.0024194717407226562,
              "curve": [
                0.24257424473762512,
                0,
                0.6757425665855408,
                0.6999999284744263
              ]
            },
            {
              "time": 0.9333333373069763,
              "angle": -0.0003523826599121094
            }
          ],
          "translate": [
            {
              "time": 0,
              "x": -0.13903427124023438,
              "y": -0.0314173698425293,
              "curve": [
                0.3467429280281067,
                0.5988385677337646,
                0.681277871131897,
                1.0000007152557373
              ]
            },
            {
              "time": 0.10000000149011612,
              "x": 0,
              "y": 0,
              "curve": [
                0.25,
                0,
                0.75,
                1
              ]
            },
            {
              "time": 0.5666666626930237,
              "x": -0.6420135498046875,
              "y": -0.14507675170898438,
              "curve": [
                0.344392865896225,
                -0.5564204454421997,
                0.692072331905365,
                0.5151889324188232
              ]
            },
            {
              "time": 0.9333333373069763,
              "x": -0.13903427124023438,
              "y": -0.0314173698425293
            }
          ],
          "scale": [
            {
              "time": 0,
              "x": 1,
              "y": 1,
              "curve": "stepped"
            },
            {
              "time": 0.10000000149011612,
              "x": 1,
              "y": 1,
              "curve": "stepped"
            },
            {
              "time": 0.5666666626930237,
              "x": 1,
              "y": 1,
              "curve": "stepped"
            },
            {
              "time": 0.9333333373069763,
              "x": 1,
              "y": 1
            }
          ]
        },
        "left_arm": {
          "rotate": [
            {
              "time": 0,
              "angle": -1.25799560546875,
              "curve": [
                0.3467429280281067,
                0.5988385677337646,
                0.681277871131897,
                1.0000007152557373
              ]
            },
            {
              "time": 0.10000000149011612,
              "angle": 0
            },
            {
              "time": 0.5666666626930237,
              "angle": -5.809074401855469,
              "curve": [
                0.344392865896225,
                -0.5564204454421997,
                0.692072331905365,
                0.5151889324188232
              ]
            },
            {
              "time": 0.9333333373069763,
              "angle": -1.25799560546875
            }
          ],
          "translate": [
            {
              "time": 0,
              "x": 0.03927040100097656,
              "y": 0.212968647480011,
              "curve": [
                0.3467429280281067,
                0.5988385677337646,
                0.681277871131897,
                1.0000007152557373
              ]
            },
            {
              "time": 0.10000000149011612,
              "x": 0,
              "y": 0,
              "curve": [
                0.25,
                0,
                0.75,
                1
              ]
            },
            {
              "time": 0.5666666626930237,
              "x": 0.18134307861328125,
              "y": 0.983428955078125,
              "curve": [
                0.344392865896225,
                -0.5564204454421997,
                0.692072331905365,
                0.5151889324188232
              ]
            },
            {
              "time": 0.9333333373069763,
              "x": 0.03927040100097656,
              "y": 0.212968647480011
            }
          ],
          "scale": [
            {
              "time": 0,
              "x": 1,
              "y": 1,
              "curve": "stepped"
            },
            {
              "time": 0.10000000149011612,
              "x": 1,
              "y": 1,
              "curve": "stepped"
            },
            {
              "time": 0.5666666626930237,
              "x": 1,
              "y": 1,
              "curve": "stepped"
            },
            {
              "time": 0.9333333373069763,
              "x": 1,
              "y": 1
            }
          ]
        },
        "left_lower_leg": {
          "rotate": [
            {
              "time": 0,
              "angle": 0,
              "curve": "stepped"
            },
            {
              "time": 0.46666666865348816,
              "angle": 0,
              "curve": "stepped"
            },
            {
              "time": 0.9333333373069763,
              "angle": 0
            }
          ],
          "translate": [
            {
              "time": 0,
              "x": 0,
              "y": 0,
              "curve": [
                0.22142857313156128,
                -0.8121442794799805,
                0.7528571486473083,
                1
              ]
            },
            {
              "time": 0.46666666865348816,
              "x": -1.5850372314453125,
              "y": 1.220306396484375,
              "curve": [
                0.3528571128845215,
                -0.5800899267196655,
                0.7099999785423279,
                1.0000003576278687
              ]
            },
            {
              "time": 0.9333333373069763,
              "x": 0,
              "y": 0
            }
          ],
          "scale": [
            {
              "time": 0,
              "x": 1,
              "y": 1,
              "curve": "stepped"
            },
            {
              "time": 0.46666666865348816,
              "x": 1,
              "y": 1,
              "curve": "stepped"
            },
            {
              "time": 0.9333333373069763,
              "x": 1,
              "y": 1
            }
          ]
        },
        "left_forearm": {
          "rotate": [
            {
              "time": 0,
              "angle": 2.270660400390625,
              "curve": [
                0.38552528619766235,
                0.5653163194656372,
                0.7361244559288025,
                1
              ]
            },
            {
              "time": 0.13333334028720856,
              "angle": 0
            },
            {
              "time": 0.6000000238418579,
              "angle": 6.063568115234375,
              "curve": [
                0.2159510850906372,
                -0.8793661594390869,
                0.6478533148765564,
                0.27091285586357117
              ]
            },
            {
              "time": 0.9333333373069763,
              "angle": 2.270660400390625
            }
          ],
          "translate": [
            {
              "time": 0,
              "x": 0,
              "y": 0,
              "curve": "stepped"
            },
            {
              "time": 0.13333334028720856,
              "x": 0,
              "y": 0,
              "curve": "stepped"
            },
            {
              "time": 0.6000000238418579,
              "x": 0,
              "y": 0,
              "curve": "stepped"
            },
            {
              "time": 0.9333333373069763,
              "x": 0,
              "y": 0
            }
          ],
          "scale": [
            {
              "time": 0,
              "x": 1,
              "y": 1,
              "curve": "stepped"
            },
            {
              "time": 0.13333334028720856,
              "x": 1,
              "y": 1,
              "curve": "stepped"
            },
            {
              "time": 0.6000000238418579,
              "x": 1,
              "y": 1,
              "curve": "stepped"
            },
            {
              "time": 0.9333333373069763,
              "x": 1,
              "y": 1
            }
          ]
        },
        "left_hair": {
          "rotate": [
            {
              "time": 0,
              "angle": -0.601287841796875,
              "curve": [
                0.3467429280281067,
                0.5988385677337646,
                0.681277871131897,
                1.0000007152557373
              ]
            },
            {
              "time": 0.10000000149011612,
              "angle": 0
            },
            {
              "time": 0.5666666626930237,
              "angle": -2.776580810546875,
              "curve": [
                0.344392865896225,
                -0.5564204454421997,
                0.692072331905365,
                0.5151889324188232
              ]
            },
            {
              "time": 0.9333333373069763,
              "angle": -0.601287841796875
            }
          ],
          "translate": [
            {
              "time": 0,
              "x": 0,
              "y": 0,
              "curve": "stepped"
            },
            {
              "time": 0.10000000149011612,
              "x": 0,
              "y": 0,
              "curve": "stepped"
            },
            {
              "time": 0.5666666626930237,
              "x": 0,
              "y": 0,
              "curve": "stepped"
            },
            {
              "time": 0.9333333373069763,
              "x": 0,
              "y": 0
            }
          ],
          "scale": [
            {
              "time": 0,
              "x": 1,
              "y": 1,
              "curve": "stepped"
            },
            {
              "time": 0.10000000149011612,
              "x": 1,
              "y": 1,
              "curve": "stepped"
            },
            {
              "time": 0.5666666626930237,
              "x": 1,
              "y": 1,
              "curve": "stepped"
            },
            {
              "time": 0.9333333373069763,
              "x": 1,
              "y": 1
            }
          ]
        },
        "left_hand": {
          "rotate": [
            {
              "time": 0,
              "angle": 0.17990589141845703,
              "curve": [
                0.38235288858413696,
                0.5625000596046448,
                0.7379679083824158,
                1
              ]
            },
            {
              "time": 0.1666666716337204,
              "angle": 0
            },
            {
              "time": 0.6333333253860474,
              "angle": 0.5738630294799805,
              "curve": [
                0.24378110468387604,
                0,
                0.6442786455154419,
                0.5833333134651184
              ]
            },
            {
              "time": 0.9333333373069763,
              "angle": 0.17990589141845703
            }
          ],
          "translate": [
            {
              "time": 0,
              "x": 0,
              "y": 0,
              "curve": "stepped"
            },
            {
              "time": 0.1666666716337204,
              "x": 0,
              "y": 0,
              "curve": "stepped"
            },
            {
              "time": 0.6333333253860474,
              "x": 0,
              "y": 0,
              "curve": "stepped"
            },
            {
              "time": 0.9333333373069763,
              "x": 0,
              "y": 0
            }
          ],
          "scale": [
            {
              "time": 0,
              "x": 1,
              "y": 1,
              "curve": "stepped"
            },
            {
              "time": 0.1666666716337204,
              "x": 1,
              "y": 1,
              "curve": "stepped"
            },
            {
              "time": 0.6333333253860474,
              "x": 1,
              "y": 1,
              "curve": "stepped"
            },
            {
              "time": 0.9333333373069763,
              "x": 1,
              "y": 1
            }
          ]
        },
        "hips": {
          "rotate": [
            {
              "time": 0,
              "angle": 0,
              "curve": [
                0.25285714864730835,
                -0.8172504305839539,
                0.75,
                1
              ]
            },
            {
              "time": 0.46666666865348816,
              "angle": -0.4250001907348633,
              "curve": [
                0.24142856895923615,
                -0.3963759243488312,
                0.7642857432365417,
                1
              ]
            },
            {
              "time": 0.9333333373069763,
              "angle": 0
            }
          ],
          "translate": [
            {
              "time": 0,
              "x": 0,
              "y": 0,
              "curve": [
                0.25285714864730835,
                -0.8172504305839539,
                0.75,
                1
              ]
            },
            {
              "time": 0.46666666865348816,
              "x": 0,
              "y": 3,
              "curve": [
                0.24142856895923615,
                -0.3963759243488312,
                0.7642857432365417,
                1
              ]
            },
            {
              "time": 0.9333333373069763,
              "x": 0,
              "y": 0
            }
          ],
          "scale": [
            {
              "time": 0,
              "x": 1,
              "y": 1,
              "curve": "stepped"
            },
            {
              "time": 0.46666666865348816,
              "x": 1,
              "y": 1,
              "curve": "stepped"
            },
            {
              "time": 0.9333333373069763,
              "x": 1,
              "y": 1
            }
          ]
        },
        "right_arm": {
          "rotate": [
            {
              "time": 0,
              "angle": -0.49419403076171875,
              "curve": [
                0.38097110390663147,
                0.5960237979888916,
                0.7244461178779602,
                1
              ]
            },
            {
              "time": 0.10000000149011612,
              "angle": 0
            },
            {
              "time": 0.5666666626930237,
              "angle": -2,
              "curve": [
                0.21537241339683533,
                -0.8036481738090515,
                0.6676543951034546,
                0.4330739974975586
              ]
            },
            {
              "time": 0.9333333373069763,
              "angle": -0.49419403076171875
            }
          ],
          "translate": [
            {
              "time": 0,
              "x": 0.02178192138671875,
              "y": -0.14399337768554688,
              "curve": [
                0.37643659114837646,
                0.6111112236976624,
                0.7183906435966492,
                1
              ]
            },
            {
              "time": 0.10000000149011612,
              "x": 0,
              "y": 0,
              "curve": [
                0.25,
                0,
                0.75,
                1
              ]
            },
            {
              "time": 0.5666666626930237,
              "x": 0.14957427978515625,
              "y": -0.9887542724609375,
              "curve": [
                0.24257424473762512,
                0,
                0.6757425665855408,
                0.6999999284744263
              ]
            },
            {
              "time": 0.9333333373069763,
              "x": 0.02178192138671875,
              "y": -0.14399337768554688
            }
          ],
          "scale": [
            {
              "time": 0,
              "x": 1,
              "y": 1,
              "curve": "stepped"
            },
            {
              "time": 0.10000000149011612,
              "x": 1,
              "y": 1,
              "curve": "stepped"
            },
            {
              "time": 0.5666666626930237,
              "x": 1,
              "y": 1,
              "curve": "stepped"
            },
            {
              "time": 0.9333333373069763,
              "x": 1,
              "y": 1
            }
          ]
        },
        "right_lower_leg": {
          "rotate": [
            {
              "time": 0,
              "angle": 0,
              "curve": [
                0.22142857313156128,
                -0.8121442794799805,
                0.7528571486473083,
                1
              ]
            },
            {
              "time": 0.46666666865348816,
              "angle": -4,
              "curve": [
                0.3528571128845215,
                -0.5800899267196655,
                0.7099999785423279,
                1.0000003576278687
              ]
            },
            {
              "time": 0.9333333373069763,
              "angle": 0
            }
          ],
          "translate": [
            {
              "time": 0,
              "x": 0,
              "y": 0,
              "curve": [
                0.22142857313156128,
                -0.8121442794799805,
                0.7528571486473083,
                1
              ]
            },
            {
              "time": 0.46666666865348816,
              "x": -3.1143646240234375,
              "y": 0.5484085083007812,
              "curve": [
                0.3528571128845215,
                -0.5800899267196655,
                0.7099999785423279,
                1.0000003576278687
              ]
            },
            {
              "time": 0.9333333373069763,
              "x": 0,
              "y": 0
            }
          ],
          "scale": [
            {
              "time": 0,
              "x": 1,
              "y": 1,
              "curve": "stepped"
            },
            {
              "time": 0.46666666865348816,
              "x": 1,
              "y": 1,
              "curve": "stepped"
            },
            {
              "time": 0.9333333373069763,
              "x": 1,
              "y": 1
            }
          ]
        },
        "right_forearm": {
          "rotate": [
            {
              "time": 0,
              "angle": 0.2657623291015625,
              "curve": [
                0.3812154531478882,
                0.5882353186607361,
                0.7292818427085876,
                1
              ]
            },
            {
              "time": 0.13333334028720856,
              "angle": 0
            },
            {
              "time": 0.6000000238418579,
              "angle": 1.1844635009765625,
              "curve": [
                0.24257425963878632,
                0,
                0.6584157943725586,
                0.6363635659217834
              ]
            },
            {
              "time": 0.9333333373069763,
              "angle": 0.2657623291015625
            }
          ],
          "translate": [
            {
              "time": 0,
              "x": -0.2689781188964844,
              "y": -0.2605491578578949,
              "curve": [
                0.38552528619766235,
                0.5653163194656372,
                0.7361244559288025,
                1
              ]
            },
            {
              "time": 0.13333334028720856,
              "x": 0,
              "y": 0
            },
            {
              "time": 0.6000000238418579,
              "x": -0.7182769775390625,
              "y": -0.695770263671875,
              "curve": [
                0.2159510850906372,
                -0.8793661594390869,
                0.6478533148765564,
                0.27091285586357117
              ]
            },
            {
              "time": 0.9333333373069763,
              "x": -0.2689781188964844,
              "y": -0.2605491578578949
            }
          ],
          "scale": [
            {
              "time": 0,
              "x": 1,
              "y": 1,
              "curve": "stepped"
            },
            {
              "time": 0.13333334028720856,
              "x": 1,
              "y": 1,
              "curve": "stepped"
            },
            {
              "time": 0.6000000238418579,
              "x": 1,
              "y": 1,
              "curve": "stepped"
            },
            {
              "time": 0.9333333373069763,
              "x": 1,
              "y": 1
            }
          ]
        },
        "right_hair01": {
          "rotate": [
            {
              "time": 0,
              "angle": 0.61962890625,
              "curve": [
                0.38097110390663147,
                0.5960237979888916,
                0.7244461178779602,
                1
              ]
            },
            {
              "time": 0.10000000149011612,
              "angle": 0
            },
            {
              "time": 0.5666666626930237,
              "angle": -357.49237060546875,
              "curve": [
                0.21537241339683533,
                -0.8036481738090515,
                0.6676543951034546,
                0.4330739974975586
              ]
            },
            {
              "time": 0.9333333373069763,
              "angle": 0.61962890625
            }
          ],
          "translate": [
            {
              "time": 0,
              "x": 0,
              "y": 0,
              "curve": "stepped"
            },
            {
              "time": 0.10000000149011612,
              "x": 0,
              "y": 0,
              "curve": "stepped"
            },
            {
              "time": 0.5666666626930237,
              "x": 0,
              "y": 0,
              "curve": "stepped"
            },
            {
              "time": 0.9333333373069763,
              "x": 0,
              "y": 0
            }
          ],
          "scale": [
            {
              "time": 0,
              "x": 1,
              "y": 1,
              "curve": "stepped"
            },
            {
              "time": 0.10000000149011612,
              "x": 1,
              "y": 1,
              "curve": "stepped"
            },
            {
              "time": 0.5666666626930237,
              "x": 1,
              "y": 1,
              "curve": "stepped"
            },
            {
              "time": 0.9333333373069763,
              "x": 1,
              "y": 1
            }
          ]
        },
        "right_hand": {
          "rotate": [
            {
              "time": 0,
              "angle": 0.8422775268554688,
              "curve": [
                0.38235288858413696,
                0.5625000596046448,
                0.7379679083824158,
                1
              ]
            },
            {
              "time": 0.1666666716337204,
              "angle": 0,
              "curve": [
                0.3528571128845215,
                -0.5800899267196655,
                0.7099999785423279,
                1.0000003576278687
              ]
            },
            {
              "time": 0.6333333253860474,
              "angle": 2.6866965293884277,
              "curve": [
                0.22092361748218536,
                -0.6325479745864868,
                0.6757075786590576,
                0.3344618082046509
              ]
            },
            {
              "time": 0.9333333373069763,
              "angle": 0.8422775268554688
            }
          ],
          "translate": [
            {
              "time": 0,
              "x": 0,
              "y": 0,
              "curve": "stepped"
            },
            {
              "time": 0.1666666716337204,
              "x": 0,
              "y": 0,
              "curve": "stepped"
            },
            {
              "time": 0.6333333253860474,
              "x": 0,
              "y": 0,
              "curve": "stepped"
            },
            {
              "time": 0.9333333373069763,
              "x": 0,
              "y": 0
            }
          ],
          "scale": [
            {
              "time": 0,
              "x": 1,
              "y": 1,
              "curve": "stepped"
            },
            {
              "time": 0.1666666716337204,
              "x": 1,
              "y": 1,
              "curve": "stepped"
            },
            {
              "time": 0.6333333253860474,
              "x": 1,
              "y": 1,
              "curve": "stepped"
            },
            {
              "time": 0.9333333373069763,
              "x": 1,
              "y": 1
            }
          ]
        },
        "scarf": {
          "rotate": [
            {
              "time": 0,
              "angle": 0
            },
            {
              "time": 0.46666666865348816,
              "angle": 1
            },
            {
              "time": 0.9333333373069763,
              "angle": 0
            }
          ],
          "translate": [
            {
              "time": 0,
              "x": 0,
              "y": 0,
              "curve": "stepped"
            },
            {
              "time": 0.46666666865348816,
              "x": 0,
              "y": 0,
              "curve": "stepped"
            },
            {
              "time": 0.9333333373069763,
              "x": 0,
              "y": 0
            }
          ],
          "scale": [
            {
              "time": 0,
              "x": 1,
              "y": 1,
              "curve": "stepped"
            },
            {
              "time": 0.46666666865348816,
              "x": 1,
              "y": 1,
              "curve": "stepped"
            },
            {
              "time": 0.9333333373069763,
              "x": 1,
              "y": 1
            }
          ]
        },
        "spine": {
          "rotate": [
            {
              "time": 0,
              "angle": 0.01061248779296875,
              "curve": [
                0.3535030484199524,
                0.6500003933906555,
                0.6878982782363892,
                1
              ]
            },
            {
              "time": 0.03333333507180214,
              "angle": 0
            },
            {
              "time": 0.5,
              "angle": 0.43495941162109375,
              "curve": [
                0.24623115360736847,
                0,
                0.7211055159568787,
                0.8749999403953552
              ]
            },
            {
              "time": 0.9333333373069763,
              "angle": 0.01061248779296875
            }
          ],
          "translate": [
            {
              "time": 0,
              "x": 0,
              "y": 0.024390220642089844,
              "curve": [
                0.3535030484199524,
                0.6500003933906555,
                0.6878982782363892,
                1
              ]
            },
            {
              "time": 0.03333333507180214,
              "x": 0,
              "y": 0
            },
            {
              "time": 0.5,
              "x": 0,
              "y": 1,
              "curve": [
                0.24623115360736847,
                0,
                0.7211055159568787,
                0.8749999403953552
              ]
            },
            {
              "time": 0.9333333373069763,
              "x": 0,
              "y": 0.024390220642089844
            }
          ],
          "scale": [
            {
              "time": 0,
              "x": 1.0004878044128418,
              "y": 1.0004878044128418,
              "curve": [
                0.3535030484199524,
                0.6500003933906555,
                0.6878982782363892,
                1
              ]
            },
            {
              "time": 0.03333333507180214,
              "x": 1,
              "y": 1,
              "curve": [
                0.3528571128845215,
                -0.5800899267196655,
                0.7099999785423279,
                1.0000003576278687
              ]
            },
            {
              "time": 0.5,
              "x": 1.0199999809265137,
              "y": 1.0199999809265137,
              "curve": [
                0.24623115360736847,
                0,
                0.7211055159568787,
                0.8749999403953552
              ]
            },
            {
              "time": 0.9333333373069763,
              "x": 1.0004878044128418,
              "y": 1.0004878044128418
            }
          ]
        },
        "right_shoulder": {
          "rotate": [
            {
              "time": 0,
              "angle": 0,
              "curve": "stepped"
            },
            {
              "time": 0.06666667014360428,
              "angle": 0,
              "curve": "stepped"
            },
            {
              "time": 0.5333333611488342,
              "angle": 0,
              "curve": "stepped"
            },
            {
              "time": 0.9333333373069763,
              "angle": 0
            }
          ],
          "translate": [
            {
              "time": 0,
              "x": -0.3461341857910156,
              "y": -0.02524566650390625,
              "curve": [
                0.3735993206501007,
                0.6202709078788757,
                0.7121174335479736,
                1
              ]
            },
            {
              "time": 0.06666667014360428,
              "x": 0,
              "y": 0,
              "curve": [
                0.25,
                0,
                0.75,
                1
              ]
            },
            {
              "time": 0.5333333611488342,
              "x": -2.0816650390625,
              "y": -0.15182781219482422,
              "curve": [
                0.19678716361522675,
                -1.2747536897659302,
                0.6866615414619446,
                0.47426509857177734
              ]
            },
            {
              "time": 0.9333333373069763,
              "x": -0.3461341857910156,
              "y": -0.02524566650390625
            }
          ],
          "scale": [
            {
              "time": 0,
              "x": 0.9973745346069336,
              "y": 0.9973745346069336,
              "curve": [
                0.3715488314628601,
                0.6226787567138672,
                0.7096322774887085,
                1
              ]
            },
            {
              "time": 0.06666667014360428,
              "x": 1,
              "y": 1,
              "curve": [
                0.22142857313156128,
                -0.8121442794799805,
                0.7528571486473083,
                1
              ]
            },
            {
              "time": 0.5333333611488342,
              "x": 0.9803922176361084,
              "y": 0.9803922176361084,
              "curve": [
                0.2160678207874298,
                -0.7717671990394592,
                0.6914170384407043,
                0.5940236449241638
              ]
            },
            {
              "time": 0.9333333373069763,
              "x": 0.9973745346069336,
              "y": 0.9973745346069336
            }
          ]
        },
        "right_leg": {
          "rotate": [
            {
              "time": 0,
              "angle": 0,
              "curve": [
                0.22142857313156128,
                -0.8121442794799805,
                0.7528571486473083,
                1
              ]
            },
            {
              "time": 0.46666666865348816,
              "angle": 8.879493713378906,
              "curve": [
                0.3528571128845215,
                -0.5800899267196655,
                0.7099999785423279,
                1.0000003576278687
              ]
            },
            {
              "time": 0.9333333373069763,
              "angle": 0
            }
          ],
          "translate": [
            {
              "time": 0,
              "x": 0,
              "y": 0,
              "curve": [
                0.22142857313156128,
                -0.8121442794799805,
                0.7528571486473083,
                1
              ]
            },
            {
              "time": 0.46666666865348816,
              "x": -5.3091278076171875,
              "y": -5.655143737792969,
              "curve": [
                0.3528571128845215,
                -0.5800899267196655,
                0.7099999785423279,
                1.0000003576278687
              ]
            },
            {
              "time": 0.9333333373069763,
              "x": 0,
              "y": 0
            }
          ],
          "scale": [
            {
              "time": 0,
              "x": 1.0199999809265137,
              "y": 1,
              "curve": [
                0.22142857313156128,
                -0.8121442794799805,
                0.7528571486473083,
                1
              ]
            },
            {
              "time": 0.46666666865348816,
              "x": 1.0601272583007812,
              "y": 1,
              "curve": [
                0.3528571128845215,
                -0.5800899267196655,
                0.7099999785423279,
                1.0000003576278687
              ]
            },
            {
              "time": 0.9333333373069763,
              "x": 1.0199999809265137,
              "y": 1
            }
          ]
        },
        "right_foot": {
          "rotate": [
            {
              "time": 0,
              "angle": 0,
              "curve": "stepped"
            },
            {
              "time": 0.46666666865348816,
              "angle": 0,
              "curve": "stepped"
            },
            {
              "time": 0.9333333373069763,
              "angle": 0
            }
          ],
          "translate": [
            {
              "time": 0,
              "x": 0,
              "y": 0,
              "curve": "stepped"
            },
            {
              "time": 0.46666666865348816,
              "x": 0,
              "y": 0,
              "curve": "stepped"
            },
            {
              "time": 0.9333333373069763,
              "x": 0,
              "y": 0
            }
          ],
          "scale": [
            {
              "time": 0,
              "x": 1,
              "y": 1,
              "curve": "stepped"
            },
            {
              "time": 0.46666666865348816,
              "x": 1,
              "y": 1,
              "curve": "stepped"
            },
            {
              "time": 0.9333333373069763,
              "x": 1,
              "y": 1
            }
          ]
        },
        "left_leg": {
          "rotate": [
            {
              "time": 0,
              "angle": 0,
              "curve": [
                0.22142857313156128,
                -0.8121442794799805,
                0.7528571486473083,
                1
              ]
            },
            {
              "time": 0.46666666865348816,
              "angle": -1,
              "curve": [
                0.3528571128845215,
                -0.5800899267196655,
                0.7099999785423279,
                1.0000003576278687
              ]
            },
            {
              "time": 0.9333333373069763,
              "angle": 0
            }
          ],
          "translate": [
            {
              "time": 0,
              "x": 0,
              "y": 0,
              "curve": [
                0.22142857313156128,
                -0.8121442794799805,
                0.7528571486473083,
                1
              ]
            },
            {
              "time": 0.46666666865348816,
              "x": -0.8755226135253906,
              "y": 0.4466552734375,
              "curve": [
                0.3528571128845215,
                -0.5800899267196655,
                0.7099999785423279,
                1.0000003576278687
              ]
            },
            {
              "time": 0.9333333373069763,
              "x": 0,
              "y": 0
            }
          ],
          "scale": [
            {
              "time": 0,
              "x": 1,
              "y": 1,
              "curve": [
                0.22142857313156128,
                -0.8121442794799805,
                0.7528571486473083,
                1
              ]
            },
            {
              "time": 0.46666666865348816,
              "x": 1.0286812782287598,
              "y": 1,
              "curve": [
                0.3528571128845215,
                -0.5800899267196655,
                0.7099999785423279,
                1.0000003576278687
              ]
            },
            {
              "time": 0.9333333373069763,
              "x": 1,
              "y": 1
            }
          ]
        },
        "left_shoulder": {
          "rotate": [
            {
              "time": 0,
              "angle": -1.3348922729492188,
              "curve": [
                0.3735993206501007,
                0.6202709078788757,
                0.7121174335479736,
                1
              ]
            },
            {
              "time": 0.06666667014360428,
              "angle": -2,
              "curve": [
                0.25,
                0,
                0.75,
                1
              ]
            },
            {
              "time": 0.5333333611488342,
              "angle": 2,
              "curve": [
                0.19678716361522675,
                -1.2747536897659302,
                0.6866615414619446,
                0.47426509857177734
              ]
            },
            {
              "time": 0.9333333373069763,
              "angle": -1.3348922729492188
            }
          ],
          "translate": [
            {
              "time": 0,
              "x": -1.0168647766113281,
              "y": -0.004971504211425781,
              "curve": [
                0.3715488314628601,
                0.6226787567138672,
                0.7096322774887085,
                1
              ]
            },
            {
              "time": 0.06666667014360428,
              "x": -0.9994964599609375,
              "y": -0.03163337707519531,
              "curve": [
                0.22142857313156128,
                -0.8121442794799805,
                0.7528571486473083,
                1
              ]
            },
            {
              "time": 0.5333333611488342,
              "x": -1.1291961669921875,
              "y": 0.1674814224243164,
              "curve": [
                0.2160678207874298,
                -0.7717671990394592,
                0.6914170384407043,
                0.5940236449241638
              ]
            },
            {
              "time": 0.9333333373069763,
              "x": -1.0168647766113281,
              "y": -0.004971504211425781
            }
          ],
          "scale": [
            {
              "time": 0,
              "x": 0.9973745346069336,
              "y": 0.9973745346069336,
              "curve": [
                0.3715488314628601,
                0.6226787567138672,
                0.7096322774887085,
                1
              ]
            },
            {
              "time": 0.06666667014360428,
              "x": 1,
              "y": 1,
              "curve": [
                0.2014285773038864,
                -1.3031266927719116,
                0.7528571486473083,
                1
              ]
            },
            {
              "time": 0.5333333611488342,
              "x": 0.9803922176361084,
              "y": 0.9803922176361084,
              "curve": [
                0.2160678207874298,
                -0.7717671990394592,
                0.6914170384407043,
                0.5940236449241638
              ]
            },
            {
              "time": 0.9333333373069763,
              "x": 0.9973745346069336,
              "y": 0.9973745346069336
            }
          ]
        },
        "left_foot": {
          "rotate": [
            {
              "time": 0,
              "angle": 0,
              "curve": "stepped"
            },
            {
              "time": 0.46666666865348816,
              "angle": 0,
              "curve": "stepped"
            },
            {
              "time": 0.9333333373069763,
              "angle": 0
            }
          ],
          "translate": [
            {
              "time": 0,
              "x": 0,
              "y": 0,
              "curve": "stepped"
            },
            {
              "time": 0.46666666865348816,
              "x": 0,
              "y": 0,
              "curve": "stepped"
            },
            {
              "time": 0.9333333373069763,
              "x": 0,
              "y": 0
            }
          ],
          "scale": [
            {
              "time": 0,
              "x": 1,
              "y": 1,
              "curve": "stepped"
            },
            {
              "time": 0.46666666865348816,
              "x": 1,
              "y": 1,
              "curve": "stepped"
            },
            {
              "time": 0.9333333373069763,
              "x": 1,
              "y": 1
            }
          ]
        }
      }
    }
  }
}